{"data":{"site":{"siteMetadata":{"title":"Carcaras","author":"Diogo Ferreira"}},"markdownRemark":{"id":"7b807c89-205b-53bc-ab89-35954c130b48","excerpt":"R$ 4.90","html":"<h1>R$ 4.90</h1>","frontmatter":{"title":"Água Tônica - R$4.90","date":"March 07, 2011","description":"Água Tônica","thumbnail":null}}},"pageContext":{"isCreatedByStatefulCreatePages":false,"slug":"/outros/agua_tonica/","previous":{"fields":{"slug":"/outros/h20_limoneto/"},"frontmatter":{"title":"H2O Limoneto - R$5.00","tags":["Outros"]}},"next":{"fields":{"slug":"/outros/agua_sem_gas/"},"frontmatter":{"title":"Água sem gás - R$2.50","tags":["Outros"]}}}}