{"data":{"site":{"siteMetadata":{"title":"Carcaras","author":"Diogo Ferreira"}},"allMarkdownRemark":{"totalCount":1,"edges":[{"node":{"excerpt":"R$ 15.00","fields":{"slug":"/lanches/x_tudo/"},"frontmatter":{"date":"April 01, 2020","title":"X-Tudo - R$15.00","description":"Lanche X-Tudo- R$ 15.00","tags":["lanches","x-tudo"],"thumbnail":{"childImageSharp":{"fluid":{"base64":null,"aspectRatio":null,"src":null,"srcSet":null,"sizes":null}}}}}}]}},"pageContext":{"isCreatedByStatefulCreatePages":false,"tag":"x-tudo"}}